google_patent_scraper/__init__.py
google_patent_scraper/errors.py
google_patent_scraper/main.py
google_patent_scraper-1.0.8.dist-info/LICENSE
google_patent_scraper-1.0.8.dist-info/METADATA
google_patent_scraper-1.0.8.dist-info/WHEEL
google_patent_scraper-1.0.8.dist-info/top_level.txt
google_patent_scraper-1.0.8.dist-info/RECORD
