Metadata-Version: 2.1
Name: google-patent-scraper
Version: 1.0.8
Summary: A package to scrape patents from 'https://patents.google.com/'
Home-page: https://github.com/rls542/patent_scraper/
Author: Ryan Stevens
Author-email: ryan.louis.stevens@gmail.com
License: UNKNOWN
Platform: UNKNOWN
Classifier: Programming Language :: Python :: 3
Classifier: License :: OSI Approved :: MIT License
Classifier: Operating System :: OS Independent
Requires-Python: >=3.6
